vpp_papi/__init__.py
vpp_papi/macaddress.py
vpp_papi/vpp_format.py
vpp_papi/vpp_papi.py
vpp_papi/vpp_papi_async.py
vpp_papi/vpp_serializer.py
vpp_papi/vpp_stats.py
vpp_papi/vpp_transport_socket.py
vpp_papi/data/memclnt.api.json
vpp_papi/tests/__init__.py
vpp_papi/tests/test_macaddress.py
vpp_papi/tests/test_vpp_format.py
vpp_papi/tests/test_vpp_papi.py
vpp_papi/tests/test_vpp_serializer.py
vpp_papi-2.3.0.dist-info/LICENSE.txt
vpp_papi-2.3.0.dist-info/METADATA
vpp_papi-2.3.0.dist-info/WHEEL
vpp_papi-2.3.0.dist-info/top_level.txt
vpp_papi-2.3.0.dist-info/zip-safe
vpp_papi-2.3.0.dist-info/RECORD
